handsome_log/__init__.py
handsome_log/config.py
handsome_log/levels.py
handsome_log/logger.py
handsome_log/loop.py
handsome_log-0.1.1.dist-info/licenses/LICENSE.md
handsome_log-0.1.1.dist-info/METADATA
handsome_log-0.1.1.dist-info/WHEEL
handsome_log-0.1.1.dist-info/top_level.txt
handsome_log-0.1.1.dist-info/RECORD
