Metadata-Version: 2.4
Name: handsome_log
Version: 0.1.1
Summary: Universal logger with custom levels for ETL and automation processes.
Author: Pedro Dellazzari
Classifier: Programming Language :: Python :: 3
Classifier: Operating System :: OS Independent
Requires-Python: >=3.7
License-File: LICENSE.md
Requires-Dist: colorlog>=6.7.0
Dynamic: author
Dynamic: classifier
Dynamic: description
Dynamic: description-content-type
Dynamic: license-file
Dynamic: requires-dist
Dynamic: requires-python
Dynamic: summary
